json_composite_encoder/__init__.py
json_composite_encoder-1.0.0.dist-info/LICENSE
json_composite_encoder-1.0.0.dist-info/METADATA
json_composite_encoder-1.0.0.dist-info/WHEEL
json_composite_encoder-1.0.0.dist-info/top_level.txt
json_composite_encoder-1.0.0.dist-info/RECORD
